meander.py
greek_key_meander-0.0.6.dist-info/licenses/LICENSE
greek_key_meander-0.0.6.dist-info/METADATA
greek_key_meander-0.0.6.dist-info/WHEEL
greek_key_meander-0.0.6.dist-info/entry_points.txt
greek_key_meander-0.0.6.dist-info/top_level.txt
greek_key_meander-0.0.6.dist-info/RECORD
