Metadata-Version: 2.4
Name: greek_key_meander
Version: 0.0.6
Summary: A package for generating Greek key meanders
Author-email: bqiao <bqiaodev@gmail.com>
Project-URL: Homepage, https://github.com/bingqiao/greek_key_meander
Project-URL: Bug Tracker, https://github.com/bingqiao/greek_key_meander/issues
Classifier: Programming Language :: Python :: 3
Classifier: License :: OSI Approved :: MIT License
Classifier: Operating System :: OS Independent
Requires-Python: >=3.7
License-File: LICENSE
Requires-Dist: drawsvg
Requires-Dist: cairosvg
Dynamic: license-file
